backintime/__init__.py
backintime/candles.py
backintime/indicator_params.py
backintime/timeframes.py
backintime/trading_strategy.py
backintime/utils.py
backintime/analyser/__init__.py
backintime/analyser/analyser.py
backintime/analyser/indicators/__init__.py
backintime/analyser/indicators/adx.py
backintime/analyser/indicators/atr.py
backintime/analyser/indicators/base.py
backintime/analyser/indicators/bbands.py
backintime/analyser/indicators/constants.py
backintime/analyser/indicators/dmi.py
backintime/analyser/indicators/ema.py
backintime/analyser/indicators/macd.py
backintime/analyser/indicators/pivot.py
backintime/analyser/indicators/rsi.py
backintime/analyser/indicators/sma.py
backintime/broker/__init__.py
backintime/broker/base.py
backintime/broker/default/__init__.py
backintime/broker/default/balance.py
backintime/broker/default/broker.py
backintime/broker/default/fees.py
backintime/broker/default/orders.py
backintime/broker/default/proxy.py
backintime/broker/default/repo.py
backintime/broker/default/validators.py
backintime/data/__init__.py
backintime/data/binance.py
backintime/data/candle.py
backintime/data/csv.py
backintime/data/data_provider.py
backintime/result/__init__.py
backintime/result/csv.py
backintime/result/result.py
backintime/result/stats.py
backintime-1.6.3.dist-info/LICENSE
backintime-1.6.3.dist-info/METADATA
backintime-1.6.3.dist-info/WHEEL
backintime-1.6.3.dist-info/top_level.txt
backintime-1.6.3.dist-info/RECORD
