Metadata-Version: 2.1
Name: backintime
Version: 1.6.3
Summary: Tool for testing trading strategies on historical data
Home-page: https://github.com/akim-mukhtarov/backintime
Author: Akim Mukhtarov
Author-email: akim.int80h@gmail.com
Classifier: Programming Language :: Python
Classifier: Programming Language :: Python :: 3
Classifier: Programming Language :: Python :: 3 :: Only
Classifier: Development Status :: 4 - Beta
Classifier: Intended Audience :: Developers
Classifier: Intended Audience :: Financial and Insurance Industry
Classifier: License :: OSI Approved :: MIT License
Classifier: Operating System :: OS Independent
Classifier: Topic :: Software Development :: Libraries :: Python Modules
License-File: LICENSE
Requires-Dist: certifi (==2021.10.8)
Requires-Dist: charset-normalizer (==2.0.12)
Requires-Dist: idna (==3.3)
Requires-Dist: numpy (==1.22.2)
Requires-Dist: pandas (==1.4.1)
Requires-Dist: python-dateutil (==2.8.2)
Requires-Dist: pytz (==2021.3)
Requires-Dist: requests (==2.27.1)
Requires-Dist: six (==1.16.0)
Requires-Dist: ta (==0.9.0)
Requires-Dist: urllib3 (==1.26.8)
